{"nodes": [{"id": "f_geral_projetos_vida_ativa_lib_features_auth_ui_splash_screen_dart", "label": "splash_screen.dart", "file_type": "code", "source_file": "F:\\_geral\\Projetos\\vida_ativa\\lib\\features\\auth\\ui\\splash_screen.dart", "source_location": null}, {"id": "f_geral_projetos_vida_ativa_lib_features_auth_ui_splash_screen_dart_splashscreen", "label": "SplashScreen", "file_type": "code", "source_file": "F:\\_geral\\Projetos\\vida_ativa\\lib\\features\\auth\\ui\\splash_screen.dart", "source_location": null}, {"id": "f_geral_projetos_vida_ativa_lib_features_auth_ui_splash_screen_dart_build", "label": "build", "file_type": "code", "source_file": "F:\\_geral\\Projetos\\vida_ativa\\lib\\features\\auth\\ui\\splash_screen.dart", "source_location": null}, {"id": "f_geral_projetos_vida_ativa_lib_features_auth_ui_splash_screen_dart_scaffold", "label": "Scaffold", "file_type": "code", "source_file": "F:\\_geral\\Projetos\\vida_ativa\\lib\\features\\auth\\ui\\splash_screen.dart", "source_location": null}, {"id": "package_flutter_material_dart", "label": "package:flutter/material.dart", "file_type": "code", "source_file": "F:\\_geral\\Projetos\\vida_ativa\\lib\\features\\auth\\ui\\splash_screen.dart", "source_location": null}, {"id": "package_vida_ativa_core_theme_app_theme_dart", "label": "package:vida_ativa/core/theme/app_theme.dart", "file_type": "code", "source_file": "F:\\_geral\\Projetos\\vida_ativa\\lib\\features\\auth\\ui\\splash_screen.dart", "source_location": null}], "edges": [{"source": "f_geral_projetos_vida_ativa_lib_features_auth_ui_splash_screen_dart", "target": "f_geral_projetos_vida_ativa_lib_features_auth_ui_splash_screen_dart_splashscreen", "relation": "defines", "confidence": "EXTRACTED", "confidence_score": 1.0, "source_file": "F:\\_geral\\Projetos\\vida_ativa\\lib\\features\\auth\\ui\\splash_screen.dart", "source_location": null, "weight": 1.0}, {"source": "f_geral_projetos_vida_ativa_lib_features_auth_ui_splash_screen_dart", "target": "f_geral_projetos_vida_ativa_lib_features_auth_ui_splash_screen_dart_build", "relation": "defines", "confidence": "EXTRACTED", "confidence_score": 1.0, "source_file": "F:\\_geral\\Projetos\\vida_ativa\\lib\\features\\auth\\ui\\splash_screen.dart", "source_location": null, "weight": 1.0}, {"source": "f_geral_projetos_vida_ativa_lib_features_auth_ui_splash_screen_dart", "target": "f_geral_projetos_vida_ativa_lib_features_auth_ui_splash_screen_dart_scaffold", "relation": "defines", "confidence": "EXTRACTED", "confidence_score": 1.0, "source_file": "F:\\_geral\\Projetos\\vida_ativa\\lib\\features\\auth\\ui\\splash_screen.dart", "source_location": null, "weight": 1.0}, {"source": "f_geral_projetos_vida_ativa_lib_features_auth_ui_splash_screen_dart", "target": "package_flutter_material_dart", "relation": "imports", "confidence": "EXTRACTED", "confidence_score": 1.0, "source_file": "F:\\_geral\\Projetos\\vida_ativa\\lib\\features\\auth\\ui\\splash_screen.dart", "source_location": null, "weight": 1.0}, {"source": "f_geral_projetos_vida_ativa_lib_features_auth_ui_splash_screen_dart", "target": "package_vida_ativa_core_theme_app_theme_dart", "relation": "imports", "confidence": "EXTRACTED", "confidence_score": 1.0, "source_file": "F:\\_geral\\Projetos\\vida_ativa\\lib\\features\\auth\\ui\\splash_screen.dart", "source_location": null, "weight": 1.0}]}